aio_androidtv/__init__.py
aio_androidtv/adb_manager.py
aio_androidtv/androidtv.py
aio_androidtv/basetv.py
aio_androidtv/constants.py
aio_androidtv/exceptions.py
aio_androidtv/firetv.py
aio_androidtv-0.0.4.dist-info/LICENSE
aio_androidtv-0.0.4.dist-info/METADATA
aio_androidtv-0.0.4.dist-info/WHEEL
aio_androidtv-0.0.4.dist-info/top_level.txt
aio_androidtv-0.0.4.dist-info/RECORD
