Metadata-Version: 2.1
Name: aio-androidtv
Version: 0.0.4
Summary: Communicate with an Android TV or Fire TV device via ADB over a network.
Home-page: https://github.com/JeffLIrion/aio-androidtv/
Author: Jeff Irion
Author-email: jefflirion@users.noreply.github.com
License: MIT
Keywords: adb,android,androidtv,firetv
Platform: UNKNOWN
Classifier: License :: OSI Approved :: MIT License
Classifier: Operating System :: OS Independent
Classifier: Programming Language :: Python :: 3
Requires-Python: >=3.7
Requires-Dist: aio-adb-shell
